<pairstrade>
<pair>
<name>a1209-a1301</name>
<time>15:00:00</time>
<firstprice>4261</firstprice>
<secondprice>4328</secondprice>
</pair>
<pair>
<name>c1209-c1301</name>
<time>15:00:00</time>
<firstprice>2368</firstprice>
<secondprice>2252</secondprice>
</pair>
<pair>
<name>c1207-c1209</name>
<time>15:00:00</time>
<firstprice>2406</firstprice>
<secondprice>2368</secondprice>
</pair>
<pair>
<name>CF209-CF301</name>
<time>14:59:59</time>
<firstprice>18675</firstprice>
<secondprice>19435</secondprice>
</pair>
<pair>
<name>CF207-CF209</name>
<time>14:59:59</time>
<firstprice>18240</firstprice>
<secondprice>18675</secondprice>
</pair>
<pair>
<name>CF209-CF211</name>
<time>14:59:59</time>
<firstprice>18675</firstprice>
<secondprice>19130</secondprice>
</pair>
<pair>
<name>CF211-CF301</name>
<time>14:59:59</time>
<firstprice>19130</firstprice>
<secondprice>19435</secondprice>
</pair>
<pair>
<name>CF301-CF303</name>
<time>14:59:59</time>
<firstprice>19435</firstprice>
<secondprice>19625</secondprice>
</pair>
<pair>
<name>ER209-ER301</name>
<time>14:59:59</time>
<firstprice>2618</firstprice>
<secondprice>2635</secondprice>
</pair>
<pair>
<name>j1209-j1301</name>
<time>15:00:00</time>
<firstprice>1883</firstprice>
<secondprice>1909</secondprice>
</pair>
<pair>
<name>l1209-l1301</name>
<time>15:00:00</time>
<firstprice>9875</firstprice>
<secondprice>10085</secondprice>
</pair>
<pair>
<name>m1301-m1303</name>
<time>15:00:00</time>
<firstprice>3137</firstprice>
<secondprice>3100</secondprice>
</pair>
<pair>
<name>RO209-RO301</name>
<time>14:59:59</time>
<firstprice>10410</firstprice>
<secondprice>10054</secondprice>
</pair>
<pair>
<name>SR301-SR305</name>
<time>14:59:59</time>
<firstprice>5969</firstprice>
<secondprice>6025</secondprice>
</pair>
<pair>
<name>SR209-SR211</name>
<time>14:59:59</time>
<firstprice>6178</firstprice>
<secondprice>6136</secondprice>
</pair>
<pair>
<name>v1209-v1301</name>
<time>14:59:59</time>
<firstprice>6630</firstprice>
<secondprice>6810</secondprice>
</pair>
<pair>
<name>WS209-WS301</name>
<time>14:59:59</time>
<firstprice>2359</firstprice>
<secondprice>2446</secondprice>
</pair>
<pair>
<name>WS301-WS305</name>
<time>14:59:59</time>
<firstprice>2446</firstprice>
<secondprice>2493</secondprice>
</pair>
<pair>
<name>y1301-y1305</name>
<time>15:00:00</time>
<firstprice>9338</firstprice>
<secondprice>9204</secondprice>
</pair>
</pairstrade>
